<?xml version="1.0" encoding="UTF-8"?>
<Language name="Czech" characters="512">
  <Section name="unmapped">
    <String id="95">Změnit pohled: </String>
    <String id="96">Řadit podle: </String>
    <String id="97">Zobrazit podle: </String>
    <String id="98">Typ řazení: </String>
    <String id="100">Ikony</String>
    <String id="101">Seznam</String>
    <String id="103">Jména</String>
    <String id="104">Datum přidání</String>
    <String id="127">Objekty</String>
    <String id="135">Žánry</String>
    <String id="137">Vyhledávat</String>
    <String id="154">Uložení</String>
    <String id="174">Žánr</String>
    <String id="184">Obnovit</String>
    <String id="199">Režisér</String>
    <String id="201">Rok</String>
    <String id="203">Nastínit zápletku</String>
    <String id="204">Hodnocení</String>
    <String id="205">Hlasů</String>
    <String id="208">Přehrát</String>
    <String id="209">Další</String>
    <String id="210">Předchozí</String>
    <String id="219">Prosím, vložte disk</String>
    <String id="299">Délka</String>
    <String id="330">To může nějakou dobu trvat ...</String>
    <String id="342">Filmy</String>
    <String id="344">Herci</String>
    <String id="345">Rok</String>
    <String id="366">Rok</String>
    <String id="367">Hodnocení</String>
    <String id="369">Titul</String>
    <String id="417">Velké ikony</String>
    <String id="432">Odstranit film z databáze</String>
    <String id="433">Jste si jisti, že chcete odstranit?</String>
    <String id="457">Změnit zobrazení</String>
    <String id="496">Volby</String>
    <String id="529">Velké ikony seznam</String>
    <String id="621">Datum</String>
    <String id="712">Zpátky</String>
    <String id="733">Filmový pás</String>
    <String id="791">3D Filmový pás</String>
    <String id="792">Rozložení Menu</String>
    <String id="863">Soubor</String>
    <String id="875">Aktuální program</String>
    <String id="900">Pokračovat v přehrávání v místě přerušení?</String>
    <String id="905">Je třeba nastavit tento modul první</String>
    <String id="921">Soubor je stažený</String>
    <String id="924">Menu</String>
    <String id="927">Varování</String>
    <String id="931">Hodnocení</String>
    <String id="936">Pokračovat od:</String>
    <String id="985">Stahování detaily filmů</String>
    <String id="1011">Životopis</String>
    <String id="1951">Pevný disk</String>
    <String id="2084">Začátek</String>
    <String id="2085">Konec</String>
    <String id="2086">Vpřed</String>
    <String id="2087">Zaostalý</String>
    <String id="2998">min</String>
    <String id="4514">Stáhnout fanart (všechny filmy)</String>
    <String id="5910">Získejte informace o filmu z internetu (vybraný film)</String>
    <String id="6022">Vyberte si MyFilms DB Config</String>
    <String id="6029">Změnit</String>
    <String id="7986">Filmy Hlavní</String>
    <String id="7987">Detaily o filmu</String>
    <String id="7988">Hodnocení filmu</String>
    <String id="7989">Herci</String>
    <String id="7990">Žádné nové příspěvky</String>
    <String id="7991">Herci Info</String>
    <String id="7992">Films obal manažer</String>
    <String id="7993">Films více vybraných</String>
    <String id="7994">Films Fanart manažer</String>
    <String id="7997">Films/Image Select</String>
    <String id="200026">Krajina</String>
    <String id="200027">Shlédnuté</String>
    <String id="200028">shlédnuté</String>
    <String id="200029">Neshlédnuté</String>
    <String id="200036">Ruční ladění</String>
    <String id="107986">Filmy</String>
    <String id="107987">Filmy</String>
    <String id="107988">Filmy</String>
    <String id="1079818">Odstranit uživatelský profil</String>
    <String id="1079819">Zobrazení Menu</String>
    <String id="1079820">Smazat položku menu</String>
    <String id="1079821">Přesun položku menu nahoru</String>
    <String id="1079822">Přesun položku menu dolů</String>
    <String id="1079823">Přidat do menu jako vlastní zobrazení</String>
    <String id="1079824">Přejmenovat položku menu</String>
    <String id="1079825">Nastavit Film hodnota filtru</String>
    <String id="1079826">Nastavit Zobrazení výrazu filtru</String>
    <String id="1079827">Zakázat položku menu</String>
    <String id="1079828">Povolit položku menu</String>
    <String id="1079829">Uložit aktuální vlastní nastavení zobrazení</String>
    <String id="1079830">Odstranit film ...</String>
    <String id="1079831">Odstranit film z katalogu</String>
    <String id="1079832">Smazat filmový soubor(y) z disku</String>
    <String id="1079833">Odstranit z katalogu a disku</String>
    <String id="1079834">Pokud potvrdíte, budou mediální soubory fyzicky odstraněny!</String>
    <String id="1079835">Jste si jisti, že chcete smazat film?</String>
    <String id="1079836">Přidat do box setu ...</String>
    <String id="1079837">Odstranit z box setu</String>
    <String id="1079838">Zadejte nový box set jméno ...</String>
    <String id="1079839">Reverzní jména ({0})</String>
    <String id="1079840">Vyberte si uživatelský profil ('{0}')</String>
    <String id="1079841">Změnit výchozí zobrazení ('{0}')</String>
    <String id="1079842">Změnit výchozí konfiguraci ('{0}')</String>
    <String id="1079843">Uživatelem definované DB aktualizace (AMCupdater)</String>
    <String id="1079844">Zobrazit indexované hodnoty ({0})</String>
    <String id="1079845">Nerozdělovat hodnoty ({0})</String>
    <String id="1079846">Hotovo ...</String>
    <String id="1079847">MyFilms Fanart Tvůrce</String>
    <String id="1079848">Vytvoření nového Fanart z filmu</String>
    <String id="1079849">Vytvořit vícenásobné fanart z filmu</String>
    <String id="1079850">Aktualizace on-line dostupnosti</String>
    <String id="1079851">Vytvořit jednu fanart  mozaiku z filmu</String>
    <String id="1079852">Vytvořit  fanart "momentku" z aktuální pozice přehrávání</String>
    <String id="1079853">Vytvoření obou: jednu mozaiku a vícenásobnou Fanart z filmu</String>
    <String id="1079854">Filmová DB již v provozu (uzamčeno) !</String>
    <String id="1079855">Zastavit update DB filmu (aktivní)</String>
    <String id="1079856">Globální aktualizace byla zrušena!</String>
    <String id="1079857">Stáhnout TMDb data (online)</String>
    <String id="1079858">Ruční výběr pomocí klávesnice</String>
    <String id="1079859">Vyberte Prohledat</String>
    <String id="1079860">Ruční výběr</String>
    <String id="1079861">Aktualizovat DB (AMC Updater)</String>
    <String id="1079862">Stáhnout fanart (vybraný film)</String>
    <String id="1079863">Ruční výběr Grabber script ({0})</String>
    <String id="1079864">Automaticky co nejlépe odpovídaly ({0})</String>
    <String id="1079865">Virtuální cesta prohlížení ({0})</String>
    <String id="1079866">Hledat příbuzné filmy osob</String>
    <String id="1079867">Vybrané osoby</String>
    <String id="1079868">Herec</String>
    <String id="1079869">Režisér</String>
    <String id="1079870">Výběr</String>
    <String id="1079871">Zobrazit prázdné hodnoty ve zhlédnutí ({0})</String>
    <String id="1079872">První</String>
    <String id="1079873">Poslední</String>
    <String id="1079874">Smazat fanart (vybraný film)</String>
    <String id="1079875">Soubor '{0}' neexistuje!</String>
    <String id="1079876">Adresář '{0}' neexistuje!</String>
    <String id="1079877">Zkontrolujte prosím své nastavení!</String>
    <String id="1079878">Přejete si vybrat?</String>
    <String id="1079879">Info o propojené osobě</String>
    <String id="1079880">Vždy používej Default Start pohled ({0})</String>
    <String id="1079881">Prosím, vyberte hodnotu minimální hodnocení</String>
    <String id="1079882">Aktualizace osoba info (IMDB)</String>
    <String id="1079883">Aktualizace informací pro všechny zúčastněné osoby (IMDB)</String>
    <String id="1079884">Podrobnosti pro vybranou osobu</String>
    <String id="1079885">Filmografie pro vybranou osobu (IMDB)</String>
    <String id="1079886">Zobrazit IMDB webové stránky pro vybranou osobu</String>
    <String id="1079887">Filmové klipy pro vybranej film (IMDB)</String>
    <String id="1079888">Fotografie pro vybranej film (IMDB)</String>
    <String id="1079889">Zobrazit IMDB webové stránky pro vybranej film</String>
    <String id="1079890">Filmové klipy pro vybranou osobu (IMDB)</String>
    <String id="1079891">Fotografie pro vybranou osobu (IMDB)</String>
    <String id="1079892">Aktualizace ...</String>
    <String id="1079893">Filmografie (TMDB)</String>
    <String id="1079894">Označit za shlédnuté</String>
    <String id="1079895">Označit za neshlédnuté</String>
    <String id="1079896">Osoby</String>
    <String id="1079897">Užití pohledu Seznam pro skupiny ({0})</String>
    <String id="1079898">Zeptat, jestli WOL by měla být zaslána ({0})</String>
    <String id="1079899">Získejte z internetu info o osobě(Zvolená osoba)</String>
    <String id="1079900">Stáhněte osobě obrázky (Vybraný film)</String>
    <String id="1079901">Pohled (dispozice) ...</String>
    <String id="1079902">Řadit podle ...</String>
    <String id="1079903">Změna zobrazení ...</String>
    <String id="1079904">Kontextové volby ...</String>
    <String id="1079905">Seřadit podle (Kolekce) ...</String>
    <String id="1079906">Pohled</String>
    <String id="1079907">Osoby</String>
    <String id="1079908">Skupina</String>
    <String id="1079909">Vyberte roli</String>
    <String id="1079910">Počítat</String>
    <String id="1079918">Cache trailers for online content ({0})</String>
    <String id="1079919">Always ask for playback quality for online content ({0})</String>
    <String id="1079920">Vždy používat Default Start Config ({0})</String>
    <String id="1079921">Získat online informace ({0})</String>
    <String id="1079930">Cast and Crew for selected film (IMDb)</String>
    <String id="10798500">Přehrát Film (externí přehrávač)</String>
    <String id="10798600">Search OnlineVideos ...</String>
    <String id="10798601">Search MyFilms ...</String>
    <String id="10798608">Hledat všechny osoby podle role</String>
    <String id="10798609">Poslední hledání ...</String>
    <String id="10798610">Filmy jako </String>
    <String id="10798611">Funkce výběru</String>
    <String id="10798612">Producent</String>
    <String id="10798613">Vyberte si vlastnost k vyhledávání</String>
    <String id="10798614">Hledat příbuzné filmy podle vlastností</String>
    <String id="10798615">Vyhledat všechny filmy podle vlastností</String>
    <String id="10798616">Hledat na všechny vlastnosti</String>
    <String id="10798617">Hledat vlastnosti </String>
    <String id="10798618">Globální úsilí o hledání řetězec "{0} '</String>
    <String id="10798619">=&gt; {0} záznam (y) pro výraz {1}</String>
    <String id="10798620">Informace o osobě</String>
    <String id="10798621">Vyhledávání Náhodné filmy</String>
    <String id="10798622">Vše</String>
    <String id="10798623">(bez info)</String>
    <String id="10798624">Filmy informační systém</String>
    <String id="10798625">Žádný výsledek pro tuto hodnotu!</String>
    <String id="10798626">=&gt; '{1}' ({0})</String>
    <String id="10798627">Jediné slovo</String>
    <String id="10798628">zapnuto</String>
    <String id="10798629">vypnuto</String>
    <String id="10798630">Nová hodnota</String>
    <String id="10798631">Zobrazit NAS Server status</String>
    <String id="10798632">Filtrovaný</String>
    <String id="10798633">New Search</String>
    <String id="10798636">Název souboru</String>
    <String id="10798637">Žádná zhoda pro tenhle pohled!</String>
    <String id="10798638">Zobrazit celý seznam filmů</String>
    <String id="10798639">Žádné filmy nalezeny!</String>
    <String id="10798640">Žádna položka odpovídající hledané hodnotě.</String>
    <String id="10798641">Žádnej vstup pro vyhledávat.</String>
    <String id="10798642">Aktualizovat údaje o vlastnosti filmu</String>
    <String id="10798643">Vyberte vlastnost pro aktualizaci</String>
    <String id="10798644">Špatnej vstupní formát. Prosím zkuste to znovu.</String>
    <String id="10798645">Globální vyhledávání (celoplošně)</String>
    <String id="10798646">Vyhledávání filmů</String>
    <String id="10798647">Vyhledávání herce</String>
    <String id="10798648">Zdroj</String>
    <String id="10798649">Trailery</String>
    <String id="10798650">Číslo v Katalogu</String>
    <String id="10798651">Zkontrolováno</String>
    <String id="10798652">Štítek Média</String>
    <String id="10798653">Typ Média</String>
    <String id="10798654">Zdroj</String>
    <String id="10798655">Datum</String>
    <String id="10798656">Půjčené</String>
    <String id="10798657">Hodnocení</String>
    <String id="10798658">Originální Název</String>
    <String id="10798659">Preložený Název</String>
    <String id="10798660">Formátovaný Název</String>
    <String id="10798661">Režisér</String>
    <String id="10798662">Producent</String>
    <String id="10798663">Krajina</String>
    <String id="10798664">Kategorie</String>
    <String id="10798665">Rok</String>
    <String id="10798666">Délka</String>
    <String id="10798667">Herci</String>
    <String id="10798668">URL</String>
    <String id="10798669">Popis</String>
    <String id="10798670">Komentáře</String>
    <String id="10798671">Video Formát</String>
    <String id="10798672">Video Bitrate</String>
    <String id="10798673">Audio Formát</String>
    <String id="10798674">Audio Bitrate</String>
    <String id="10798675">Rozlišení</String>
    <String id="10798676">Počet Snímků</String>
    <String id="10798677">Jazyky</String>
    <String id="10798678">Titulky</String>
    <String id="10798679">Datum Přidání</String>
    <String id="10798680">Velikost</String>
    <String id="10798681">Disky</String>
    <String id="10798682">Obrázek</String>
    <String id="10798683">Osvědčení</String>
    <String id="10798684">Autor</String>
    <String id="10798685">Sledované</String>
    <String id="10798686">Datum Sledováni</String>
    <String id="10798687">IMDB Id</String>
    <String id="10798688">TMDB Id</String>
    <String id="10798689">Globální nastavení ...</String>
    <String id="10798690">Globální aktualizace ...</String>
    <String id="10798691">Zobrazit pouze filmy s trailerem ({0})</String>
    <String id="10798692">Zobrazit pouze filmy s minimálním hodnocením ({0})</String>
    <String id="10798693">Změna minimální hodnocení od '{0}'</String>
    <String id="10798694">Hledat a přidat místní trailer (všechny filmy)</String>
    <String id="10798695">Hledání Traileru hotovo!</String>
    <String id="10798696">Zobrazit pouze neshlédnuté filmy ({0})</String>
    <String id="10798697">Poměr</String>
    <String id="10798698">Obrazový Formát</String>
    <String id="10798699">Wiki Nápověda online (Web)</String>
    <String id="10798700">Filmy informační systém ...</String>
    <String id="10798701">Možnosti ...</String>
    <String id="10798702">Aktualizace ...</String>
    <String id="10798703">Fanart a Obal ...</String>
    <String id="10798704">Trailer ...</String>
    <String id="10798705">Trailer nalezen!</String>
    <String id="10798706">Vyberte si internet Grabber script</String>
    <String id="10798707">Titulky ...</String>
    <String id="10798708">Aktualizace Mediainfo</String>
    <String id="10798709">Přehrát Film</String>
    <String id="10798710">Přehrát Trailer</String>
    <String id="10798711">YouTube Trailer (OnlineVideos)</String>
    <String id="10798712">Apple iTunes Trailer (OnlineVideos)</String>
    <String id="10798713">Nezhlédnuté filmy " ({0})</String>
    <String id="10798714">Globální filtry ...</String>
    <String id="10798715">Nahrát osobní údaje (všechny osoby)</String>
    <String id="10798716">IMDb Trailer (OnlineVideos)</String>
    <String id="10798717">Neúplných dat filmu</String>
    <String id="10798718">=&gt; {0} Film(y) chybí '{1}'</String>
    <String id="10798719">Nahrát info pro filmy (.NFO soubor, místní, doplnění chybějících informací)</String>
    <String id="10798720">Nahrát info pro filmy (.NFO soubor, místní, nahradit všechny informace)</String>
    <String id="10798721">Nahrát info pro filmy z Ant souboru (místní)</String>
    <String id="10798722">Skladovať info pro filmy v Ant souboru (místní)</String>
    <String id="10798723">Hledat trailer (místní)</String>
    <String id="10798724">Nahrát trailer (online)</String>
    <String id="10798725">Odstranit Trailer z katalogu (vybraný film)</String>
    <String id="10798726">Hledat Trailer - všechny filmy (místní)</String>
    <String id="10798727">Zobrazit NAS Server status</String>
    <String id="10798728">Vytvořit obal z filmu</String>
    <String id="10798729">Vytvořit obal z filmu jako mozaiku</String>
    <String id="10798730">Aktualizace všech vlastností (pouze tehdy, když jsou nové údaje)</String>
    <String id="10798731">Osoba info (IMDB)</String>
    <String id="10798732">Vyberte vlastnost pro aktualizaci</String>
    <String id="10798733">Nahradit stávající obal za tenhle?</String>
    <String id="10798734">Aktualizovat všechny vlastnosti</String>
    <String id="10798735">Aktualizace pouze chybějící vlastnosti</String>
    <String id="10798736">Místně dostupné</String>
    <String id="10798737">Trailer není součástí místního</String>
    <String id="10798738">Zkusit online Trailer?</String>
    <String id="10798739">Hledat místní trailery a aktualizovat DB?</String>
    <String id="10798740">*** hrát všechny trailery ***</String>
    <String id="10798741">(aktivní)</String>
    <String id="10798742">(offline) - start?</String>
    <String id="10798743">úspěšně zahájena!</String>
    <String id="10798744">Nelze spustit!</String>
    <String id="10798745">Začátek není možný - zkontrolovat config!</String>
    <String id="10798746">není nakonfigurován pro wakeonlan!</String>
    <String id="10798747">Automatické spuštění NAS není možné ...</String>
    <String id="10798748">Globální Aktualizace skončena!</String>
    <String id="10798749">MyFilms: Stáhnout do adresáře filmu</String>
    <String id="10798751">Přehled</String>
    <String id="10798752">Popis</String>
    <String id="10798753">Komentáře</String>
    <String id="10798754">Herci</String>
    <String id="10798755">Technické Info</String>
    <String id="10798756">Extra Info</String>
    <String id="10798757">Fanart</String>
    <String id="10798758">Filmové náhledy</String>
    <String id="10798760">Download collection cover (TMDB)</String>
    <String id="10798761">Nahrát obaly (TMDb)</String>
    <String id="10798762">Změna obalu</String>
    <String id="10798763">Správce obalu...</String>
    <String id="10798764">Načíst několik obalu ...</String>
    <String id="10798765">*** Zobrazit vše ***</String>
    <String id="10798766">Načíst jeden obal ...</String>
    <String id="10798767">Fanart manažer ...</String>
    <String id="10798768">Žádný obal nalezen !</String>
    <String id="10798769">Vyberte obal jako výchozí</String>
    <String id="10798770">Zobrazit pouze filmy s médii k dispozici ({0})</String>
    <String id="10798771">Možnosti zobrazení ...</String>
    <String id="10798772">Vyberte si pole ...</String>
    <String id="10798773">Zobrazení položky</String>
    <String id="10798774">prázdný</String>
    <String id="10798775">Trakt ...</String>
    <String id="10798776">Trakt</String>
    <String id="10798777">Kalendář</String>
    <String id="10798778">Přátelé</String>
    <String id="10798779">Návrhy</String>
    <String id="10798780">Nejpopulárnější filmy</String>
    <String id="10798781">Seznam sledovaných</String>
    <String id="10798782">Výkřiky</String>
    <String id="10798783">Přidat film do seznamu sledovaných</String>
    <String id="10798784">Ohodnoť tenhle film</String>
    <String id="10798785">Přidat do seznamu...</String>
    <String id="10798786">Zobrazit seznamy ...</String>
    <String id="10798787">Zobrazit související filmy</String>
    <String id="10798790">Hlavní název</String>
    <String id="10798791">Sekundární název</String>
    <String id="10798792">Řadit Název</String>
    <String id="10798795">Odstranit všechny filmové detaily (Vybraný film)</String>
    <String id="10798797">Vyberte možnost aktualizace ...</String>
    <String id="10798798">Vyberte jedno pole pro aktualizaci ...</String>
    <String id="10798799">Výběr pole pro aktualizaci ...</String>
    <String id="10798800">Upozornění: případná Dlouhá doba chodu!</String>
    <String id="10798801">By měl trailer hledat skutečně</String>
    <String id="10798802">Začínat pre {0} filmov?</String>
    <String id="10798803">Rozšířené hledání (adresáře) ?</String>
    <String id="10798810">Odstranit obal filmu z DB</String>
    <String id="10798820">Detaily Zobrazit položku</String>
    <String id="10798825">Online informace</String>
    <String id="10798826">Populární filmy</String>
    <String id="10798827">Právě se přehrává</String>
    <String id="10798828">Nejlépe hodnocené</String>
    <String id="10798829">Připravované filmy</String>
    <String id="10798930">Víceuživatelský status</String>
    <String id="10798932">Alternativní tituly</String>
    <String id="10798933">Virtuální Cesta Název</String>
    <String id="10798940">Trailer</String>
    <String id="10798941">Slogan</String>
    <String id="10798942">Tagy</String>
    <String id="10798943">Poměr stran</String>
    <String id="10798944">Hodnocení uživatele</String>
    <String id="10798945">Fanart</String>
    <String id="10798946">Filmstudio</String>
    <String id="10798947">IMDB Toplist</String>
    <String id="10798948">Online stav</String>
    <String id="10798949">Edice</String>
    <String id="10798950">Online stav Trailer</String>
    <String id="10798951">Osoby</String>
    <String id="10798952">Trakt kategorie</String>
    <String id="10798953">Audio kanály</String>
    <String id="10798954">Nedávno přidané</String>
    <String id="10798955">Indexován Název</String>
    <String id="10798956">Věk přidání (dny)</String>
    <String id="10798957">Oblíbené</String>
    <String id="10798960">Neznámý</String>
    <String id="10798961">Dnes</String>
    <String id="10798962">Včera</String>
    <String id="10798963">Minulý týden</String>
    <String id="10798964">Minulý měsíc</String>
    <String id="10798965">Poslední 3 měsíce</String>
    <String id="10798966">Poslední rok</String>
    <String id="10798967">Poslední 3 roky</String>
    <String id="10798968">Starší než 3 roky</String>
    <String id="10798970">Globální filtr "zvolte vlastní filtr" ({0})</String>
    <String id="10798971">Globální filtr "zakázat vlastní filtr" ({0})</String>
    <String id="10798980">Přehrát náhodné ukázky</String>
    <String id="10798981">Trailer Scrobbling ...</String>
    <String id="10798982">Play next Trailer ?</String>
    <String id="10798983">Cancel</String>
    <String id="10798984">Next Trailer</String>
    <String id="10798985">Do you want to play the main movie ?</String>
    <String id="10798986">MyFilms Movie Preview</String>
    <String id="10798987">Movie Catalog ...</String>
    <String id="10798988">Cached Trailer: </String>
    <String id="10798989">Online Trailer: </String>
    <String id="10798990">Load single trailer (TMDB)</String>
    <String id="10798991">Load all trailers for these films (TMDB)</String>
    <String id="10798992">Select Movie  ...</String>
    <String id="10798993">Select Trailer ...</String>
    <String id="10798994">Select Quality ...</String>
    <String id="10798995">No matching movie found !</String>
    <String id="10798996">No trailers found !</String>
    <String id="10798997">load all</String>
    <String id="10798998">Cannot play online content !</String>
    <String id="10799201">MyFilms Správce Obalú</String>
    <String id="10799202">Rozlišení</String>
    <String id="10799203">Filtr ...</String>
    <String id="10799204">Stáhněte obaly ...</String>
    <String id="10799205">(updating...)</String>
    <String id="10799206">Filtr</String>
    <String id="10799207">Stáhněte obaly</String>
    <String id="10799211">Smazat vybraný obal</String>
    <String id="10799212">Odstranit všechny "nízké"</String>
    <String id="10799213">Odstranit všechny "střední"</String>
    <String id="10799214">Odstranit všechny "vysoké"</String>
    <String id="10799215">Odstranit všechny kromě aktuálně vybraného</String>
    <String id="10799221">Vše</String>
    <String id="10799222">Vysoké</String>
    <String id="10799223">Střední</String>
    <String id="10799224">Nízké</String>
    <String id="10799230">ke stažení: {0}</String>
    <String id="10799301">Jméno</String>
    <String id="10799302">Narozen</String>
    <String id="10799303">Místo</String>
    <String id="10799304">Životopis</String>
    <String id="10799310">Uživatelské jméno</String>
    <String id="10799401">Globální Aktualizace</String>
    <String id="10799402">Globální Filtry</String>
    <String id="10799501">Web Details ...</String>
    <String id="10799502">View Options ...</String>
  </Section>
</Language>